anilist_man/__init__.py
anilist_man/__main__.py
anilist_man/main.py
anilist_man/queries.py
anilist_man/queryFunc.py
anilist_man/refreshfunc.py
anilist_man/subFunc.py
anilist_man-0.4.3.dist-info/entry_points.txt
anilist_man-0.4.3.dist-info/LICENSE
anilist_man-0.4.3.dist-info/WHEEL
anilist_man-0.4.3.dist-info/METADATA
anilist_man-0.4.3.dist-info/RECORD
