Metadata-Version: 2.1
Name: anilist-man
Version: 0.4.3
Summary: A command-line-tool for AniList
Home-page: https://github.com/minihut/anilist-man
License: LICENSE
Keywords: anilist,anilist-cli,anilist-man,manga
Author: Mini
Requires-Python: >=3.8,<4.0
Classifier: License :: Other/Proprietary License
Classifier: Programming Language :: Python :: 3
Classifier: Programming Language :: Python :: 3.10
Classifier: Programming Language :: Python :: 3.8
Classifier: Programming Language :: Python :: 3.9
Requires-Dist: platformdirs (>=2.5.1,<3.0.0)
Requires-Dist: requests (>=2.27.1,<3.0.0)
Requires-Dist: typer[all] (>=0.4.0,<0.5.0)
Project-URL: Repository, https://github.com/minihut/anilist-man
